{"output":[{"block":"593B","street name":"Montreal Link","storey":"01 to 03","floor area (sqm)":68,"flat model":"Model A","lease commence year":2015,"remaining lease (yr)":92.58,"resale price ($)":355000,"resale registration date":"Oct 2021"},{"block":"463A","street name":"Sembawang Dr","storey":"04 to 06","floor area (sqm)":67,"flat model":"Model A","lease commence year":2015,"remaining lease (yr)":92.83,"resale price ($)":349000,"resale registration date":"Sep 2021"},{"block":"463B","street name":"Sembawang Dr","storey":"04 to 06","floor area (sqm)":67,"flat model":"Model A","lease commence year":2015,"remaining lease (yr)":92.67,"resale price ($)":340000,"resale registration date":"Sep 2021"},{"block":"463B","street name":"Sembawang Dr","storey":"04 to 06","floor area (sqm)":67,"flat model":"Model A","lease commence year":2015,"remaining lease (yr)":92.75,"resale price ($)":350000,"resale registration date":"Sep 2021"},{"block":"590A","street name":"Montreal Link","storey":"01 to 03","floor area (sqm)":68,"flat model":"Model A","lease commence year":2015,"remaining lease (yr)":92.75,"resale price ($)":330000,"resale registration date":"Aug 2021"},{"block":"463B","street name":"Sembawang Dr","storey":"07 to 09","floor area (sqm)":67,"flat model":"Model A","lease commence year":2015,"remaining lease (yr)":92.75,"resale price ($)":310000,"resale registration date":"Aug 2021"},{"block":"591A","street name":"Montreal Link","storey":"10 to 12","floor area (sqm)":68,"flat model":"Model A","lease commence year":2015,"remaining lease (yr)":93.08,"resale price ($)":320000,"resale registration date":"Apr 2021"},{"block":"592A","street name":"Montreal Link","storey":"01 to 03","floor area (sqm)":68,"flat model":"Model A","lease commence year":2015,"remaining lease (yr)":93.08,"resale price ($)":320000,"resale registration date":"Apr 2021"},{"block":"591A","street name":"Montreal Link","storey":"04 to 06","floor area (sqm)":68,"flat model":"Model A","lease commence year":2015,"remaining lease (yr)":93.25,"resale price ($)":317000,"resale registration date":"Mar 2021"},{"block":"590A","street name":"Montreal Link","storey":"04 to 06","floor area (sqm)":68,"flat model":"Model A","lease commence year":2015,"remaining lease (yr)":93.25,"resale price ($)":305000,"resale registration date":"Feb 2021"},{"block":"590A","street name":"Montreal Link","storey":"13 to 15","floor area (sqm)":68,"flat model":"Model A","lease commence year":2015,"remaining lease (yr)":93.25,"resale price ($)":320000,"resale registration date":"Feb 2021"},{"block":"593A","street name":"Montreal Link","storey":"10 to 12","floor area (sqm)":68,"flat model":"Model A","lease commence year":2015,"remaining lease (yr)":93.17,"resale price ($)":325000,"resale registration date":"Feb 2021"},{"block":"463A","street name":"Sembawang Dr","storey":"16 to 18","floor area (sqm)":67,"flat model":"Model A","lease commence year":2015,"remaining lease (yr)":93.33,"resale price ($)":322000,"resale registration date":"Feb 2021"},{"block":"463A","street name":"Sembawang Dr","storey":"04 to 06","floor area (sqm)":67,"flat model":"Model A","lease commence year":2015,"remaining lease (yr)":93.33,"resale price ($)":330000,"resale registration date":"Feb 2021"},{"block":"463B","street name":"Sembawang Dr","storey":"16 to 18","floor area (sqm)":67,"flat model":"Model A","lease commence year":2015,"remaining lease (yr)":93.33,"resale price ($)":315000,"resale registration date":"Feb 2021"},{"block":"593B","street name":"Montreal Link","storey":"04 to 06","floor area (sqm)":68,"flat model":"Model A","lease commence year":2015,"remaining lease (yr)":93.33,"resale price ($)":320000,"resale registration date":"Jan 2021"},{"block":"590B","street name":"Montreal Link","storey":"10 to 12","floor area (sqm)":68,"flat model":"Model A","lease commence year":2015,"remaining lease (yr)":93.42,"resale price ($)":300000,"resale registration date":"Nov 2020"},{"block":"593A","street name":"Montreal Link","storey":"10 to 12","floor area (sqm)":68,"flat model":"Model A","lease commence year":2015,"remaining lease (yr)":93.5,"resale price ($)":340000,"resale registration date":"Nov 2020"},{"block":"463B","street name":"Sembawang Dr","storey":"01 to 03","floor area (sqm)":67,"flat model":"Model A","lease commence year":2015,"remaining lease (yr)":93.58,"resale price ($)":270000,"resale registration date":"Nov 2020"},{"block":"593B","street name":"Montreal Link","storey":"01 to 03","floor area (sqm)":68,"flat model":"Model A","lease commence year":2015,"remaining lease (yr)":92.58,"resale price ($)":355000,"resale registration date":"Oct 2021"},{"block":"463A","street name":"Sembawang Dr","storey":"04 to 06","floor area (sqm)":67,"flat model":"Model A","lease commence year":2015,"remaining lease (yr)":92.83,"resale price ($)":349000,"resale registration date":"Sep 2021"},{"block":"463B","street name":"Sembawang Dr","storey":"04 to 06","floor area (sqm)":67,"flat model":"Model A","lease commence year":2015,"remaining lease (yr)":92.67,"resale price ($)":340000,"resale registration date":"Sep 2021"},{"block":"463B","street name":"Sembawang Dr","storey":"04 to 06","floor area (sqm)":67,"flat model":"Model A","lease commence year":2015,"remaining lease (yr)":92.75,"resale price ($)":350000,"resale registration date":"Sep 2021"},{"block":"590A","street name":"Montreal Link","storey":"01 to 03","floor area (sqm)":68,"flat model":"Model A","lease commence year":2015,"remaining lease (yr)":92.75,"resale price ($)":330000,"resale registration date":"Aug 2021"},{"block":"463B","street name":"Sembawang Dr","storey":"07 to 09","floor area (sqm)":67,"flat model":"Model A","lease commence year":2015,"remaining lease (yr)":92.75,"resale price ($)":310000,"resale registration date":"Aug 2021"},{"block":"591A","street name":"Montreal Link","storey":"10 to 12","floor area (sqm)":68,"flat model":"Model A","lease commence year":2015,"remaining lease (yr)":93.08,"resale price ($)":320000,"resale registration date":"Apr 2021"},{"block":"592A","street name":"Montreal Link","storey":"01 to 03","floor area (sqm)":68,"flat model":"Model A","lease commence year":2015,"remaining lease (yr)":93.08,"resale price ($)":320000,"resale registration date":"Apr 2021"},{"block":"591A","street name":"Montreal Link","storey":"04 to 06","floor area (sqm)":68,"flat model":"Model A","lease commence year":2015,"remaining lease (yr)":93.25,"resale price ($)":317000,"resale registration date":"Mar 2021"},{"block":"590A","street name":"Montreal Link","storey":"04 to 06","floor area (sqm)":68,"flat model":"Model A","lease commence year":2015,"remaining lease (yr)":93.25,"resale price ($)":305000,"resale registration date":"Feb 2021"},{"block":"590A","street name":"Montreal Link","storey":"13 to 15","floor area (sqm)":68,"flat model":"Model A","lease commence year":2015,"remaining lease (yr)":93.25,"resale price ($)":320000,"resale registration date":"Feb 2021"},{"block":"593A","street name":"Montreal Link","storey":"10 to 12","floor area (sqm)":68,"flat model":"Model A","lease commence year":2015,"remaining lease (yr)":93.17,"resale price ($)":325000,"resale registration date":"Feb 2021"},{"block":"463A","street name":"Sembawang Dr","storey":"16 to 18","floor area (sqm)":67,"flat model":"Model A","lease commence year":2015,"remaining lease (yr)":93.33,"resale price ($)":322000,"resale registration date":"Feb 2021"},{"block":"463A","street name":"Sembawang Dr","storey":"04 to 06","floor area (sqm)":67,"flat model":"Model A","lease commence year":2015,"remaining lease (yr)":93.33,"resale price ($)":330000,"resale registration date":"Feb 2021"},{"block":"463B","street name":"Sembawang Dr","storey":"16 to 18","floor area (sqm)":67,"flat model":"Model A","lease commence year":2015,"remaining lease (yr)":93.33,"resale price ($)":315000,"resale registration date":"Feb 2021"},{"block":"593B","street name":"Montreal Link","storey":"04 to 06","floor area (sqm)":68,"flat model":"Model A","lease commence year":2015,"remaining lease (yr)":93.33,"resale price ($)":320000,"resale registration date":"Jan 2021"},{"block":"590B","street name":"Montreal Link","storey":"10 to 12","floor area (sqm)":68,"flat model":"Model A","lease commence year":2015,"remaining lease (yr)":93.42,"resale price ($)":300000,"resale registration date":"Nov 2020"},{"block":"593A","street name":"Montreal Link","storey":"10 to 12","floor area (sqm)":68,"flat model":"Model A","lease commence year":2015,"remaining lease (yr)":93.5,"resale price ($)":340000,"resale registration date":"Nov 2020"},{"block":"463B","street name":"Sembawang Dr","storey":"01 to 03","floor area (sqm)":67,"flat model":"Model A","lease commence year":2015,"remaining lease (yr)":93.58,"resale price ($)":270000,"resale registration date":"Nov 2020"}]}